supaharrisclient/__init__.py
supaharrisclient/client.py
supaharrisclient/utils.py
supaharrisclient-1.0.dist-info/AUTHORS.txt
supaharrisclient-1.0.dist-info/LICENSE
supaharrisclient-1.0.dist-info/METADATA
supaharrisclient-1.0.dist-info/WHEEL
supaharrisclient-1.0.dist-info/top_level.txt
supaharrisclient-1.0.dist-info/RECORD
