Metadata-Version: 2.1
Name: supaharrisclient
Version: 1.0
Summary: API client for the supaharris.com globular & star cluster database
Home-page: https://github.com/tlrh314/supaharris-client
Author: Timo Halbesma
Author-email: halbesma@MPA-Garching.MPG.DE
License: AGPL-3.0
Platform: UNKNOWN
Classifier: Development Status :: 3 - Alpha
Classifier: Environment :: Console
Classifier: Framework :: Django :: 2.2
Classifier: Intended Audience :: Science/Research
Classifier: License :: OSI Approved :: GNU Affero General Public License v3
Classifier: Operating System :: OS Independent
Classifier: Programming Language :: Python :: 3.5
Classifier: Programming Language :: Python :: 3.6
Classifier: Programming Language :: Python :: 3.7
Classifier: Topic :: Database :: Front-Ends
Classifier: Topic :: Scientific/Engineering :: Astronomy
Classifier: Topic :: Scientific/Engineering :: Physics
Requires-Dist: numpy
Requires-Dist: requests
